Project/rvseed_4/core/mux_pc.v
// +FHDR----------------------------------------------------------------------------
//                 Copyright (c) 2022 
//                       ALL RIGHTS RESERVED
// ---------------------------------------------------------------------------------
// Filename      : pc_next.v
// Author        : Rongye
// Created On    : 2022-03-21 22:56
// Last Modified : 2022-04-11 20:24
// ---------------------------------------------------------------------------------
// Description   : Determine the update value of the pc. 
//
//
// -FHDR----------------------------------------------------------------------------
`include "rvseed_defines.v"

module mux_pc (
    input                       ena,
    input                       branch,  // branch type 
    input                       zero,    // alu result is zero
    input                       jump,    // jump type 
    input      [`CPU_WIDTH-1:0] imm,     // immediate  
    input      [`CPU_WIDTH-1:0] curr_pc, // current pc addr
    output reg [`CPU_WIDTH-1:0] next_pc  // next pc addr
    );

always @(*) begin
    if (~ena) 
        next_pc = curr_pc;
    else if (branch && ~zero) // bne
        next_pc = curr_pc + imm;
    else if (jump) // jal 
        next_pc = curr_pc + imm;
    else 
        next_pc = curr_pc + `CPU_WIDTH'h4;   
end
endmodule

Project/rvseed_2/core/inst_mem.v
// +FHDR----------------------------------------------------------------------------
//                 Copyright (c) 2022 
//                       ALL RIGHTS RESERVED
// ---------------------------------------------------------------------------------
// Filename      : inst_mem.v
// Author        : Rongye
// Created On    : 2022-03-22 01:33
// Last Modified : 2022-04-08 23:35
// ---------------------------------------------------------------------------------
// Description   : Instruction memory, the initial value is given by testbench. 
//
//
// -FHDR----------------------------------------------------------------------------
`include "rvseed_defines.v"
module inst_mem (
    input      [`CPU_WIDTH-1:0] curr_pc,  // current pc addr
    output reg [`CPU_WIDTH-1:0] inst      // instruction
);

    reg [`CPU_WIDTH-1:0] inst_mem_f[0:`INST_MEM_ADDR_DEPTH-1];

    always @(*) begin
        inst = inst_mem_f[curr_pc[`INST_MEM_ADDR_WIDTH+2-1:2]];
    end
endmodule

Project/rvseed_2/tb/tb_rvseed.v
// +FHDR----------------------------------------------------------------------------
//                 Copyright (c) 2022 
//                       ALL RIGHTS RESERVED
// ---------------------------------------------------------------------------------
// Filename      : tb_rvseed.v
// Author        : Rongye
// Created On    : 2022-03-25 04:18
// Last Modified : 2022-04-09 00:46
// ---------------------------------------------------------------------------------
// Description   : 
//
//
// -FHDR----------------------------------------------------------------------------
`timescale 1ns / 1ps
`include "rvseed_defines.v"

module tb_rvseed ();

    reg                   clk;
    reg                   rst_n;
    reg                   branch;
    reg                   zero;
    reg                   jump;
    reg  [`CPU_WIDTH-1:0] imm;
    reg  [       5*8-1:0] inst_name;

    wire                  ena;
    wire [`CPU_WIDTH-1:0] next_pc;
    wire [`CPU_WIDTH-1:0] curr_pc;
    wire [`CPU_WIDTH-1:0] inst;


    initial begin
        #(`SIM_PERIOD / 2);
        clk       = 1'b0;
        rst_n     = 1'b0;

        branch    = 1'b1;
        zero      = 1'b1;
        jump      = 1'b0;
        imm       = `CPU_WIDTH'h8;
        inst_name = "ADD";
        inst_load(inst_name);

        #(`SIM_PERIOD * 1);
        rst_n = 1'b1;
        #1;  // To present instant changes

        #(`SIM_PERIOD * 50);  // test branch inst (bne)
        zero = 1'b0;
        #(`SIM_PERIOD * 1);
        zero = 1'b1;
        #(`SIM_PERIOD * 50);  // test jump inst (jal)
        jump = 1'b1;
        #(`SIM_PERIOD * 1);
        jump = 1'b0;
        #(`SIM_PERIOD * 500);
        $stop;
    end

    initial begin
        #(`SIM_PERIOD * 50000);
        $display("Time Out");
        $finish;
    end

    always #(`SIM_PERIOD / 2) clk = ~clk;

    task reset;  // reset 1 clock
        begin
            rst_n = 0;
            #(`SIM_PERIOD * 1);
            rst_n = 1;
        end
    endtask

    task inst_load;
        input [5*8-1:0] inst_name;
        begin
            $readmemh(inst_name, u_inst_mem_0.inst_mem_f);
        end
    endtask


    pc_reg u_pc_reg_0 (
        .clk    (clk),
        .rst_n  (rst_n),
        .ena    (ena),
        .next_pc(next_pc),
        .curr_pc(curr_pc)
    );

    inst_mem u_inst_mem_0 (
        .curr_pc(curr_pc),
        .inst   (inst)
    );

    mux_pc u_mux_pc_0 (
        .ena    (ena),
        .branch (branch),
        .zero   (zero),
        .jump   (jump),
        .imm    (imm),
        .curr_pc(curr_pc),
        .next_pc(next_pc)
    );

    // iverilog 
    initial begin
        $dumpfile("sim_out.vcd");
        $dumpvars;
    end

endmodule

Project/rvseed_2/tb/sim_out.vcd
$date
	Mon Apr 11 05:04:03 2022
$end
$version
	Icarus Verilog
$end
$timescale
	1ps
$end
$scope module tb_rvseed $end
$var wire 32 ! next_pc [31:0] $end
$var wire 32 " inst [31:0] $end
$var wire 1 # ena $end
$var wire 32 $ curr_pc [31:0] $end
$var reg 1 % branch $end
$var reg 1 & clk $end
$var reg 32 ' imm [31:0] $end
$var reg 40 ( inst_name [39:0] $end
$var reg 1 ) jump $end
$var reg 1 * rst_n $end
$var reg 1 + zero $end
$scope module u_inst_mem_0 $end
$var wire 32 , curr_pc [31:0] $end
$var reg 32 - inst [31:0] $end
$upscope $end
$scope module u_mux_pc_0 $end
$var wire 1 % branch $end
$var wire 32 . imm [31:0] $end
$var wire 1 ) jump $end
$var wire 1 + zero $end
$var wire 1 # ena $end
$var wire 32 / curr_pc [31:0] $end
$var reg 32 0 next_pc [31:0] $end
$upscope $end
$scope module u_pc_reg_0 $end
$var wire 1 & clk $end
$var wire 32 1 next_pc [31:0] $end
$var wire 1 * rst_n $end
$var reg 32 2 curr_pc [31:0] $end
$var reg 1 # ena $end
$upscope $end
$scope task inst_load $end
$var reg 40 3 inst_name [39:0] $end
$upscope $end
$scope task reset $end
$upscope $end
$upscope $end
$enddefinitions $end
#0
$dumpvars
bx 3
bx 2
bx 1
bx 0
bx /
bx .
bx -
bx ,
x+
x*
x)
bx (
bx '
x&
x%
bx $
x#
bx "
bx !
$end
#10000
b110100010011 "
b110100010011 -
b0 !
b0 0
b0 1
0#
b0 $
b0 ,
b0 /
b0 2
b10000010100010001000100 3
b10000010100010001000100 (
b1000 '
b1000 .
0)
1+
1%
0*
1&
#20000
0&
#30000
b100 !
b100 0
b100 1
1#
1&
1*
#40000
0&
#50000
b110110010011 "
b110110010011 -
b1000 !
b1000 0
b1000 1
b100 $
b100 ,
b100 /
b100 2
1&
#60000
0&
#70000
b10010011 "
b10010011 -
b1100 !
b1100 0
b1100 1
b1000 $
b1000 ,
b1000 /
b1000 2
1&
#80000
0&
#90000
b100010011 "
b100010011 -
b10000 !
b10000 0
b10000 1
b1100 $
b1100 ,
b1100 /
b1100 2
1&
#100000
0&
#110000
b1000001000111100110011 "
b1000001000111100110011 -
b10100 !
b10100 0
b10100 1
b10000 $
b10000 ,
b10000 /
b10000 2
1&
#120000
0&
#130000
b111010010011 "
b111010010011 -
b11000 !
b11000 0
b11000 1
b10100 $
b10100 ,
b10100 /
b10100 2
1&
#140000
0&
#150000
b1000000000000110010011 "
b1000000000000110010011 -
b11100 !
b11100 0
b11100 1
b11000 $
b11000 ,
b11000 /
b11000 2
1&
#160000
0&
#170000
b1001101110111110001011001100011 "
b1001101110111110001011001100011 -
b100000 !
b100000 0
b100000 1
b11100 $
b11100 ,
b11100 /
b11100 2
1&
#180000
0&
#190000
b100000000000010010011 "
b100000000000010010011 -
b100100 !
b100100 0
b100100 1
b100000 $
b100000 ,
b100000 /
b100000 2
1&
#200000
0&
#210000
b100000000000100010011 "
b100000000000100010011 -
b101000 !
b101000 0
b101000 1
b100100 $
b100100 ,
b100100 /
b100100 2
1&
#220000
0&
#230000
b1000001000111100110011 "
b1000001000111100110011 -
b101100 !
b101100 0
b101100 1
b101000 $
b101000 ,
b101000 /
b101000 2
1&
#240000
0&
#250000
b1000000000111010010011 "
b1000000000111010010011 -
b110000 !
b110000 0
b110000 1
b101100 $
b101100 ,
b101100 /
b101100 2
1&
#260000
0&
#270000
b1100000000000110010011 "
b1100000000000110010011 -
b110100 !
b110100 0
b110100 1
b110000 $
b110000 ,
b110000 /
b110000 2
1&
#280000
0&
#290000
b1001011110111110001101001100011 "
b1001011110111110001101001100011 -
b111000 !
b111000 0
b111000 1
b110100 $
b110100 ,
b110100 /
b110100 2
1&
#300000
0&
#310000
b1100000000000010010011 "
b1100000000000010010011 -
b111100 !
b111100 0
b111100 1
b111000 $
b111000 ,
b111000 /
b111000 2
1&
#320000
0&
#330000
b11100000000000100010011 "
b11100000000000100010011 -
b1000000 !
b1000000 0
b1000000 1
b111100 $
b111100 ,
b111100 /
b111100 2
1&
#340000
0&
#350000
b1000001000111100110011 "
b1000001000111100110011 -
b1000100 !
b1000100 0
b1000100 1
b1000000 $
b1000000 ,
b1000000 /
b1000000 2
1&
#360000
0&
#370000
b101000000000111010010011 "
b101000000000111010010011 -
b1001000 !
b1001000 0
b1001000 1
b1000100 $
b1000100 ,
b1000100 /
b1000100 2
1&
#380000
0&
#390000
b10000000000000110010011 "
b10000000000000110010011 -
b1001100 !
b1001100 0
b1001100 1
b1001000 $
b1001000 ,
b1001000 /
b1001000 2
1&
#400000
0&
#410000
b1001001110111110001111001100011 "
b1001001110111110001111001100011 -
b1010000 !
b1010000 0
b1010000 1
b1001100 $
b1001100 ,
b1001100 /
b1001100 2
1&
#420000
0&
#430000
b10010011 "
b10010011 -
b1010100 !
b1010100 0
b1010100 1
b1010000 $
b1010000 ,
b1010000 /
b1010000 2
1&
#440000
0&
#450000
b11111111111111111000000100110111 "
b11111111111111111000000100110111 -
b1011000 !
b1011000 0
b1011000 1
b1010100 $
b1010100 ,
b1010100 /
b1010100 2
1&
#460000
0&
#470000
b1000001000111100110011 "
b1000001000111100110011 -
b1011100 !
b1011100 0
b1011100 1
b1011000 $
b1011000 ,
b1011000 /
b1011000 2
1&
#480000
0&
#490000
b11111111111111111000111010110111 "
b11111111111111111000111010110111 -
b1100000 !
b1100000 0
b1100000 1
b1011100 $
b1011100 ,
b1011100 /
b1011100 2
1&
#500000
0&
#510000
b10100000000000110010011 "
b10100000000000110010011 -
b1100100 !
b1100100 0
b1100100 1
b1100000 $
b1100000 ,
b1100000 /
b1100000 2
1&
#520000
0&
#530000
b1001001110111110001001001100011 "
b1001001110111110001001001100011 -
b1101000 !
b1101000 0
b1101000 1
b1100100 $
b1100100 ,
b1100100 /
b1100100 2
1&
#540000
0&
#550000
b10000000000000000000000010110111 "
b10000000000000000000000010110111 -
b1101100 !
b1101100 0
b1101100 1
b1101000 $
b1101000 ,
b1101000 /
b1101000 2
1&
#560000
0&
#570000
b100010011 "
b100010011 -
b1110000 !
b1110000 0
b1110000 1
b1101100 $
b1101100 ,
b1101100 /
b1101100 2
1&
#580000
0&
#590000
b1000001000111100110011 "
b1000001000111100110011 -
b1110100 !
b1110100 0
b1110100 1
b1110000 $
b1110000 ,
b1110000 /
b1110000 2
1&
#600000
0&
#610000
b10000000000000000000111010110111 "
b10000000000000000000111010110111 -
b1111000 !
b1111000 0
b1111000 1
b1110100 $
b1110100 ,
b1110100 /
b1110100 2
1&
#620000
0&
#630000
b11000000000000110010011 "
b11000000000000110010011 -
b1111100 !
b1111100 0
b1111100 1
b1111000 $
b1111000 ,
b1111000 /
b1111000 2
1&
#640000
0&
#650000
b1000111110111110001011001100011 "
b1000111110111110001011001100011 -
b10000000 !
b10000000 0
b10000000 1
b1111100 $
b1111100 ,
b1111100 /
b1111100 2
1&
#660000
0&
#670000
b10000000000000000000000010110111 "
b10000000000000000000000010110111 -
b10000100 !
b10000100 0
b10000100 1
b10000000 $
b10000000 ,
b10000000 /
b10000000 2
1&
#680000
0&
#690000
b11111111111111111000000100110111 "
b11111111111111111000000100110111 -
b10001000 !
b10001000 0
b10001000 1
b10000100 $
b10000100 ,
b10000100 /
b10000100 2
1&
#700000
0&
#710000
b1000001000111100110011 "
b1000001000111100110011 -
b10001100 !
b10001100 0
b10001100 1
b10001000 $
b10001000 ,
b10001000 /
b10001000 2
1&
#720000
0&
#730000
b1111111111111111000111010110111 "
b1111111111111111000111010110111 -
b10010000 !
b10010000 0
b10010000 1
b10001100 $
b10001100 ,
b10001100 /
b10001100 2
1&
#740000
0&
#750000
b11100000000000110010011 "
b11100000000000110010011 -
b10010100 !
b10010100 0
b10010100 1
b10010000 $
b10010000 ,
b10010000 /
b10010000 2
1&
#760000
0&
#770000
b1000101110111110001101001100011 "
b1000101110111110001101001100011 -
b10011000 !
b10011000 0
b10011000 1
b10010100 $
b10010100 ,
b10010100 /
b10010100 2
1&
#780000
0&
#790000
b10010011 "
b10010011 -
b10011100 !
b10011100 0
b10011100 1
b10011000 $
b10011000 ,
b10011000 /
b10011000 2
1&
#800000
0&
#810000
b1000000100110111 "
b1000000100110111 -
b10100000 !
b10100000 0
b10100000 1
b10011100 $
b10011100 ,
b10011100 /
b10011100 2
1&
#820000
0&
#830000
b11111111111100010000000100010011 "
b11111111111100010000000100010011 -
b10100100 !
b10100100 0
b10100100 1
b10100000 $
b10100000 ,
b10100000 /
b10100000 2
1&
#840000
0&
#850000
b1000001000111100110011 "
b1000001000111100110011 -
b10101000 !
b10101000 0
b10101000 1
b10100100 $
b10100100 ,
b10100100 /
b10100100 2
1&
#860000
0&
#870000
b1000111010110111 "
b1000111010110111 -
b10101100 !
b10101100 0
b10101100 1
b10101000 $
b10101000 ,
b10101000 /
b10101000 2
1&
#880000
0&
#890000
b11111111111111101000111010010011 "
b11111111111111101000111010010011 -
b10110000 !
b10110000 0
b10110000 1
b10101100 $
b10101100 ,
b10101100 /
b10101100 2
1&
#900000
0&
#910000
b100000000000000110010011 "
b100000000000000110010011 -
b10110100 !
b10110100 0
b10110100 1
b10110000 $
b10110000 ,
b10110000 /
b10110000 2
1&
#920000
0&
#930000
b1000011110111110001101001100011 "
b1000011110111110001101001100011 -
b10111000 !
b10111000 0
b10111000 1
b10110100 $
b10110100 ,
b10110100 /
b10110100 2
1&
#940000
0&
#950000
b10000000000000000000000010110111 "
b10000000000000000000000010110111 -
b10111100 !
b10111100 0
b10111100 1
b10111000 $
b10111000 ,
b10111000 /
b10111000 2
1&
#960000
0&
#970000
b11111111111100001000000010010011 "
b11111111111100001000000010010011 -
b11000000 !
b11000000 0
b11000000 1
b10111100 $
b10111100 ,
b10111100 /
b10111100 2
1&
#980000
0&
#990000
b100010011 "
b100010011 -
b11000100 !
b11000100 0
b11000100 1
b11000000 $
b11000000 ,
b11000000 /
b11000000 2
1&
#1000000
0&
#1010000
b1000001000111100110011 "
b1000001000111100110011 -
b11001000 !
b11001000 0
b11001000 1
b11000100 $
b11000100 ,
b11000100 /
b11000100 2
1&
#1020000
0&
#1030000
b10000000000000000000111010110111 "
b10000000000000000000111010110111 -
b11001100 !
b11001100 0
b11001100 1
b11001000 $
b11001000 ,
b11001000 /
b11001000 2
1&
#1031000
b11010000 !
b11010000 0
b11010000 1
0+
#1040000
0&
#1050000
b100100000000000110010011 "
b100100000000000110010011 -
b11011000 !
b11011000 0
b11011000 1
b11010000 $
b11010000 ,
b11010000 /
b11010000 2
1&
#1051000
b11010100 !
b11010100 0
b11010100 1
1+
#1060000
0&
#1070000
b1000001110111110001101001100011 "
b1000001110111110001101001100011 -
b11011000 !
b11011000 0
b11011000 1
b11010100 $
b11010100 ,
b11010100 /
b11010100 2
1&
#1080000
0&
#1090000
b10000000000000000000000010110111 "
b10000000000000000000000010110111 -
b11011100 !
b11011100 0
b11011100 1
b11011000 $
b11011000 ,
b11011000 /
b11011000 2
1&
#1100000
0&
#1110000
b11111111111100001000000010010011 "
b11111111111100001000000010010011 -
b11100000 !
b11100000 0
b11100000 1
b11011100 $
b11011100 ,
b11011100 /
b11011100 2
1&
#1120000
0&
#1130000
b1000000100110111 "
b1000000100110111 -
b11100100 !
b11100100 0
b11100100 1
b11100000 $
b11100000 ,
b11100000 /
b11100000 2
1&
#1140000
0&
#1150000
b11111111111100010000000100010011 "
b11111111111100010000000100010011 -
b11101000 !
b11101000 0
b11101000 1
b11100100 $
b11100100 ,
b11100100 /
b11100100 2
1&
#1160000
0&
#1170000
b1000001000111100110011 "
b1000001000111100110011 -
b11101100 !
b11101100 0
b11101100 1
b11101000 $
b11101000 ,
b11101000 /
b11101000 2
1&
#1180000
0&
#1190000
b10000000000000001000111010110111 "
b10000000000000001000111010110111 -
b11110000 !
b11110000 0
b11110000 1
b11101100 $
b11101100 ,
b11101100 /
b11101100 2
1&
#1200000
0&
#1210000
b11111111111011101000111010010011 "
b11111111111011101000111010010011 -
b11110100 !
b11110100 0
b11110100 1
b11110000 $
b11110000 ,
b11110000 /
b11110000 2
1&
#1220000
0&
#1230000
b101000000000000110010011 "
b101000000000000110010011 -
b11111000 !
b11111000 0
b11111000 1
b11110100 $
b11110100 ,
b11110100 /
b11110100 2
1&
#1240000
0&
#1250000
b111111110111110001100001100011 "
b111111110111110001100001100011 -
b11111100 !
b11111100 0
b11111100 1
b11111000 $
b11111000 ,
b11111000 /
b11111000 2
1&
#1260000
0&
#1270000
b10000000000000000000000010110111 "
b10000000000000000000000010110111 -
b100000000 !
b100000000 0
b100000000 1
b11111100 $
b11111100 ,
b11111100 /
b11111100 2
1&
#1280000
0&
#1290000
b1000000100110111 "
b1000000100110111 -
b100000100 !
b100000100 0
b100000100 1
b100000000 $
b100000000 ,
b100000000 /
b100000000 2
1&
#1300000
0&
#1310000
b11111111111100010000000100010011 "
b11111111111100010000000100010011 -
b100001000 !
b100001000 0
b100001000 1
b100000100 $
b100000100 ,
b100000100 /
b100000100 2
1&
#1320000
0&
#1330000
b1000001000111100110011 "
b1000001000111100110011 -
b100001100 !
b100001100 0
b100001100 1
b100001000 $
b100001000 ,
b100001000 /
b100001000 2
1&
#1340000
0&
#1350000
b10000000000000001000111010110111 "
b10000000000000001000111010110111 -
b100010000 !
b100010000 0
b100010000 1
b100001100 $
b100001100 ,
b100001100 /
b100001100 2
1&
#1360000
0&
#1370000
b11111111111111101000111010010011 "
b11111111111111101000111010010011 -
b100010100 !
b100010100 0
b100010100 1
b100010000 $
b100010000 ,
b100010000 /
b100010000 2
1&
#1380000
0&
#1390000
b101100000000000110010011 "
b101100000000000110010011 -
b100011000 !
b100011000 0
b100011000 1
b100010100 $
b100010100 ,
b100010100 /
b100010100 2
1&
#1400000
0&
#1410000
b111101110111110001100001100011 "
b111101110111110001100001100011 -
b100011100 !
b100011100 0
b100011100 1
b100011000 $
b100011000 ,
b100011000 /
b100011000 2
1&
#1420000
0&
#1430000
b10000000000000000000000010110111 "
b10000000000000000000000010110111 -
b100100000 !
b100100000 0
b100100000 1
b100011100 $
b100011100 ,
b100011100 /
b100011100 2
1&
#1440000
0&
#1450000
b11111111111100001000000010010011 "
b11111111111100001000000010010011 -
b100100100 !
b100100100 0
b100100100 1
b100100000 $
b100100000 ,
b100100000 /
b100100000 2
1&
#1460000
0&
#1470000
b11111111111111111000000100110111 "
b11111111111111111000000100110111 -
b100101000 !
b100101000 0
b100101000 1
b100100100 $
b100100100 ,
b100100100 /
b100100100 2
1&
#1480000
0&
#1490000
b1000001000111100110011 "
b1000001000111100110011 -
b100101100 !
b100101100 0
b100101100 1
b100101000 $
b100101000 ,
b100101000 /
b100101000 2
1&
#1500000
0&
#1510000
b1111111111111111000111010110111 "
b1111111111111111000111010110111 -
b100110000 !
b100110000 0
b100110000 1
b100101100 $
b100101100 ,
b100101100 /
b100101100 2
1&
#1520000
0&
#1530000
b11111111111111101000111010010011 "
b11111111111111101000111010010011 -
b100110100 !
b100110100 0
b100110100 1
b100110000 $
b100110000 ,
b100110000 /
b100110000 2
1&
#1540000
0&
#1550000
b110000000000000110010011 "
b110000000000000110010011 -
b100111000 !
b100111000 0
b100111000 1
b100110100 $
b100110100 ,
b100110100 /
b100110100 2
1&
#1560000
0&
#1570000
b111011110111110001100001100011 "
b111011110111110001100001100011 -
b100111100 !
b100111100 0
b100111100 1
b100111000 $
b100111000 ,
b100111000 /
b100111000 2
1&
#1580000
0&
#1590000
b10010011 "
b10010011 -
b101000000 !
b101000000 0
b101000000 1
b100111100 $
b100111100 ,
b100111100 /
b100111100 2
1&
#1600000
0&
#1610000
b11111111111100000000000100010011 "
b11111111111100000000000100010011 -
b101000100 !
b101000100 0
b101000100 1
b101000000 $
b101000000 ,
b101000000 /
b101000000 2
1&
#1620000
0&
#1630000
b1000001000111100110011 "
b1000001000111100110011 -
b101001000 !
b101001000 0
b101001000 1
b101000100 $
b101000100 ,
b101000100 /
b101000100 2
1&
#1640000
0&
#1650000
b11111111111100000000111010010011 "
b11111111111100000000111010010011 -
b101001100 !
b101001100 0
b101001100 1
b101001000 $
b101001000 ,
b101001000 /
b101001000 2
1&
#1660000
0&
#1670000
b110100000000000110010011 "
b110100000000000110010011 -
b101010000 !
b101010000 0
b101010000 1
b101001100 $
b101001100 ,
b101001100 /
b101001100 2
1&
#1680000
0&
#1690000
b111001110111110001110001100011 "
b111001110111110001110001100011 -
b101010100 !
b101010100 0
b101010100 1
b101010000 $
b101010000 ,
b101010000 /
b101010000 2
1&
#1700000
0&
#1710000
b11111111111100000000000010010011 "
b11111111111100000000000010010011 -
b101011000 !
b101011000 0
b101011000 1
b101010100 $
b101010100 ,
b101010100 /
b101010100 2
1&
#1720000
0&
#1730000
b100000000000100010011 "
b100000000000100010011 -
b101011100 !
b101011100 0
b101011100 1
b101011000 $
b101011000 ,
b101011000 /
b101011000 2
1&
#1740000
0&
#1750000
b1000001000111100110011 "
b1000001000111100110011 -
b101100000 !
b101100000 0
b101100000 1
b101011100 $
b101011100 ,
b101011100 /
b101011100 2
1&
#1760000
0&
#1770000
b111010010011 "
b111010010011 -
b101100100 !
b101100100 0
b101100100 1
b101100000 $
b101100000 ,
b101100000 /
b101100000 2
1&
#1780000
0&
#1790000
b111000000000000110010011 "
b111000000000000110010011 -
b101101000 !
b101101000 0
b101101000 1
b101100100 $
b101100100 ,
b101100100 /
b101100100 2
1&
#1800000
0&
#1810000
b111001110111110001000001100011 "
b111001110111110001000001100011 -
b101101100 !
b101101100 0
b101101100 1
b101101000 $
b101101000 ,
b101101000 /
b101101000 2
1&
#1820000
0&
#1830000
b11111111111100000000000010010011 "
b11111111111100000000000010010011 -
b101110000 !
b101110000 0
b101110000 1
b101101100 $
b101101100 ,
b101101100 /
b101101100 2
1&
#1840000
0&
#1850000
b11111111111100000000000100010011 "
b11111111111100000000000100010011 -
b101110100 !
b101110100 0
b101110100 1
b101110000 $
b101110000 ,
b101110000 /
b101110000 2
1&
#1860000
0&
#1870000
b1000001000111100110011 "
b1000001000111100110011 -
b101111000 !
b101111000 0
b101111000 1
b101110100 $
b101110100 ,
b101110100 /
b101110100 2
1&
#1880000
0&
#1890000
b11111111111000000000111010010011 "
b11111111111000000000111010010011 -
b101111100 !
b101111100 0
b101111100 1
b101111000 $
b101111000 ,
b101111000 /
b101111000 2
1&
#1900000
0&
#1910000
b111100000000000110010011 "
b111100000000000110010011 -
b110000000 !
b110000000 0
b110000000 1
b101111100 $
b101111100 ,
b101111100 /
b101111100 2
1&
#1920000
0&
#1930000
b110111110111110001010001100011 "
b110111110111110001010001100011 -
b110000100 !
b110000100 0
b110000100 1
b110000000 $
b110000000 ,
b110000000 /
b110000000 2
1&
#1940000
0&
#1950000
b100000000000010010011 "
b100000000000010010011 -
b110001000 !
b110001000 0
b110001000 1
b110000100 $
b110000100 ,
b110000100 /
b110000100 2
1&
#1960000
0&
#1970000
b10000000000000000000000100110111 "
b10000000000000000000000100110111 -
b110001100 !
b110001100 0
b110001100 1
b110001000 $
b110001000 ,
b110001000 /
b110001000 2
1&
#1980000
0&
#1990000
b11111111111100010000000100010011 "
b11111111111100010000000100010011 -
b110010000 !
b110010000 0
b110010000 1
b110001100 $
b110001100 ,
b110001100 /
b110001100 2
1&
#2000000
0&
#2010000
b1000001000111100110011 "
b1000001000111100110011 -
b110010100 !
b110010100 0
b110010100 1
b110010000 $
b110010000 ,
b110010000 /
b110010000 2
1&
#2020000
0&
#2030000
b10000000000000000000111010110111 "
b10000000000000000000111010110111 -
b110011000 !
b110011000 0
b110011000 1
b110010100 $
b110010100 ,
b110010100 /
b110010100 2
1&
#2040000
0&
#2050000
b1000000000000000110010011 "
b1000000000000000110010011 -
b110011100 !
b110011100 0
b110011100 1
b110011000 $
b110011000 ,
b110011000 /
b110011000 2
1&
#2051000
b110100000 !
b110100000 0
b110100000 1
1)
#2060000
0&
#2070000
b110100000000000010010011 "
b110100000000000010010011 -
b110101000 !
b110101000 0
b110101000 1
b110100000 $
b110100000 ,
b110100000 /
b110100000 2
1&
#2071000
b110100100 !
b110100100 0
b110100100 1
0)
#2080000
0&
#2090000
b101100000000000100010011 "
b101100000000000100010011 -
b110101000 !
b110101000 0
b110101000 1
b110100100 $
b110100100 ,
b110100100 /
b110100100 2
1&
#2100000
0&
#2110000
b1000001000000010110011 "
b1000001000000010110011 -
b110101100 !
b110101100 0
b110101100 1
b110101000 $
b110101000 ,
b110101000 /
b110101000 2
1&
#2120000
0&
#2130000
b1100000000000111010010011 "
b1100000000000111010010011 -
b110110000 !
b110110000 0
b110110000 1
b110101100 $
b110101100 ,
b110101100 /
b110101100 2
1&
#2140000
0&
#2150000
b1000100000000000110010011 "
b1000100000000000110010011 -
b110110100 !
b110110100 0
b110110100 1
b110110000 $
b110110000 ,
b110110000 /
b110110000 2
1&
#2160000
0&
#2170000
b110011110100001001101001100011 "
b110011110100001001101001100011 -
b110111000 !
b110111000 0
b110111000 1
b110110100 $
b110110100 ,
b110110100 /
b110110100 2
1&
#2180000
0&
#2190000
b111000000000000010010011 "
b111000000000000010010011 -
b110111100 !
b110111100 0
b110111100 1
b110111000 $
b110111000 ,
b110111000 /
b110111000 2
1&
#2200000
0&
#2210000
b101100000000000100010011 "
b101100000000000100010011 -
b111000000 !
b111000000 0
b111000000 1
b110111100 $
b110111100 ,
b110111100 /
b110111100 2
1&
#2220000
0&
#2230000
b1000001000000100110011 "
b1000001000000100110011 -
b111000100 !
b111000100 0
b111000100 1
b111000000 $
b111000000 ,
b111000000 /
b111000000 2
1&
#2240000
0&
#2250000
b1100100000000111010010011 "
b1100100000000111010010011 -
b111001000 !
b111001000 0
b111001000 1
b111000100 $
b111000100 ,
b111000100 /
b111000100 2
1&
#2260000
0&
#2270000
b1001000000000000110010011 "
b1001000000000000110010011 -
b111001100 !
b111001100 0
b111001100 1
b111001000 $
b111001000 ,
b111001000 /
b111001000 2
1&
#2280000
0&
#2290000
b110001110100010001111001100011 "
b110001110100010001111001100011 -
b111010000 !
b111010000 0
b111010000 1
b111001100 $
b111001100 ,
b111001100 /
b111001100 2
1&
#2300000
0&
#2310000
b110100000000000010010011 "
b110100000000000010010011 -
b111010100 !
b111010100 0
b111010100 1
b111010000 $
b111010000 ,
b111010000 /
b111010000 2
1&
#2320000
0&
#2330000
b100001000000010110011 "
b100001000000010110011 -
b111011000 !
b111011000 0
b111011000 1
b111010100 $
b111010100 ,
b111010100 /
b111010100 2
1&
#2340000
0&
#2350000
b1101000000000111010010011 "
b1101000000000111010010011 -
b111011100 !
b111011100 0
b111011100 1
b111011000 $
b111011000 ,
b111011000 /
b111011000 2
1&
#2360000
0&
#2370000
b1001100000000000110010011 "
b1001100000000000110010011 -
b111100000 !
b111100000 0
b111100000 1
b111011100 $
b111011100 ,
b111011100 /
b111011100 2
1&
#2380000
0&
#2390000
b110001110100001001010001100011 "
b110001110100001001010001100011 -
b111100100 !
b111100100 0
b111100100 1
b111100000 $
b111100000 ,
b111100000 /
b111100000 2
1&
#2400000
0&
#2410000
b1000010011 "
b1000010011 -
b111101000 !
b111101000 0
b111101000 1
b111100100 $
b111100100 ,
b111100100 /
b111100100 2
1&
#2420000
0&
#2430000
b110100000000000010010011 "
b110100000000000010010011 -
b111101100 !
b111101100 0
b111101100 1
b111101000 $
b111101000 ,
b111101000 /
b111101000 2
1&
#2440000
0&
#2450000
b101100000000000100010011 "
b101100000000000100010011 -
b111110000 !
b111110000 0
b111110000 1
b111101100 $
b111101100 ,
b111101100 /
b111101100 2
1&
#2460000
0&
#2470000
b1000001000111100110011 "
b1000001000111100110011 -
b111110100 !
b111110100 0
b111110100 1
b111110000 $
b111110000 ,
b111110000 /
b111110000 2
1&
#2480000
0&
#2490000
b11110000001100010011 "
b11110000001100010011 -
b111111000 !
b111111000 0
b111111000 1
b111110100 $
b111110100 ,
b111110100 /
b111110100 2
1&
#2500000
0&
#2510000
b100100000001000010011 "
b100100000001000010011 -
b111111100 !
b111111100 0
b111111100 1
b111111000 $
b111111000 ,
b111111000 /
b111111000 2
1&
#2520000
0&
#2530000
b1000000000001010010011 "
b1000000000001010010011 -
b1000000000 !
b1000000000 0
b1000000000 1
b111111100 $
b111111100 ,
b111111100 /
b111111100 2
1&
#2540000
0&
#2550000
b11111110010100100001010011100011 "
b11111110010100100001010011100011 -
b1000000100 !
b1000000100 0
b1000000100 1
b1000000000 $
b1000000000 ,
b1000000000 /
b1000000000 2
1&
#2560000
0&
#2570000
b1100000000000111010010011 "
b1100000000000111010010011 -
b1000001000 !
b1000001000 0
b1000001000 1
b1000000100 $
b1000000100 ,
b1000000100 /
b1000000100 2
1&
#2580000
0&
#2590000
b1010000000000000110010011 "
b1010000000000000110010011 -
b1000001100 !
b1000001100 0
b1000001100 1
b1000001000 $
b1000001000 ,
b1000001000 /
b1000001000 2
1&
#2600000
0&
#2610000
b101101110100110001111001100011 "
b101101110100110001111001100011 -
b1000010000 !
b1000010000 0
b1000010000 1
b1000001100 $
b1000001100 ,
b1000001100 /
b1000001100 2
1&
#2620000
0&
#2630000
b1000010011 "
b1000010011 -
b1000010100 !
b1000010100 0
b1000010100 1
b1000010000 $
b1000010000 ,
b1000010000 /
b1000010000 2
1&
#2640000
0&
#2650000
b111000000000000010010011 "
b111000000000000010010011 -
b1000011000 !
b1000011000 0
b1000011000 1
b1000010100 $
b1000010100 ,
b1000010100 /
b1000010100 2
1&
#2660000
0&
